cromdriver/__init__.py
cromdriver/cli.py
cromdriver/cromdriver.py
cromdriver-0.4.1.dist-info/LICENSE
cromdriver-0.4.1.dist-info/METADATA
cromdriver-0.4.1.dist-info/WHEEL
cromdriver-0.4.1.dist-info/entry_points.txt
cromdriver-0.4.1.dist-info/top_level.txt
cromdriver-0.4.1.dist-info/RECORD
