Metadata-Version: 2.1
Name: cromdriver
Version: 0.4.1
Summary: Auto downloader for chromedrivers
Home-page: https://github.com/Gokender/cromdriver
Author: gokender
Author-email: gauthier.chaty+pypi@outlook.com
License: UNKNOWN
Platform: UNKNOWN
Classifier: Programming Language :: Python :: 3
Classifier: License :: OSI Approved :: MIT License
Classifier: Operating System :: OS Independent
Requires-Python: >=3.6
Requires-Dist: requests
Requires-Dist: appdirs
